otter/__init__.py
otter/_version.py
otter/bootstrap.py
otter/html.py
otter/otter.conf
otter/otter.py
otter/plot.py
otter/themes/default/body.html
otter/themes/default/footer.html
otter/themes/default/head.html
otter/themes/default/header.html
otter_report-0.3.3.dist-info/AUTHORS.rst
otter_report-0.3.3.dist-info/LICENSE
otter_report-0.3.3.dist-info/METADATA
otter_report-0.3.3.dist-info/WHEEL
otter_report-0.3.3.dist-info/top_level.txt
otter_report-0.3.3.dist-info/RECORD
