Metadata-Version: 2.1
Name: otter-report
Version: 0.3.3
Summary: The simple HTML report generator for Python jobs.
Home-page: https://github.com/transientlunatic/otter
Author: Daniel Williams
Author-email: daniel.williams@glasgow.ac.uk
License: ISCL
Keywords: otter
Classifier: Development Status :: 2 - Pre-Alpha
Classifier: Intended Audience :: Developers
Classifier: License :: OSI Approved :: ISC License (ISCL)
Classifier: Natural Language :: English
Classifier: Programming Language :: Python :: 3
Classifier: Programming Language :: Python :: 3.3
Classifier: Programming Language :: Python :: 3.4
Classifier: Programming Language :: Python :: 3.5
Classifier: Programming Language :: Python :: 3.6
Classifier: Programming Language :: Python :: 3.7
Classifier: Programming Language :: Python :: 3.8
Requires-Python: >=3.3
License-File: LICENSE
License-File: AUTHORS.rst
Requires-Dist: tabulate
Requires-Dist: jinja2
Requires-Dist: markdown
Requires-Dist: pyyaml
Requires-Dist: matplotlib
Requires-Dist: configparser
